netmc/__init__.py
netmc/models.py
netmc-0.0.1.dist-info/LICENSE
netmc-0.0.1.dist-info/METADATA
netmc-0.0.1.dist-info/WHEEL
netmc-0.0.1.dist-info/top_level.txt
netmc-0.0.1.dist-info/RECORD
